urbantrips/__init__.py
urbantrips/compute_clusters.py
urbantrips/create_viz.py
urbantrips/initialize_environment.py
urbantrips/process_transactions.py
urbantrips/run_all_urbantrips.py
urbantrips/run_dashboard.py
urbantrips/run_interactive_tools.py
urbantrips/run_postprocessing.py
urbantrips/carto/__init__.py
urbantrips/carto/carto.py
urbantrips/carto/routes.py
urbantrips/carto/stops.py
urbantrips/cluster/__init__.py
urbantrips/cluster/dbscan.py
urbantrips/datamodel/__init__.py
urbantrips/datamodel/legs.py
urbantrips/datamodel/misc.py
urbantrips/datamodel/services.py
urbantrips/datamodel/transactions.py
urbantrips/datamodel/trips.py
urbantrips/destinations/__init__.py
urbantrips/destinations/destinations.py
urbantrips/geo/__init__.py
urbantrips/geo/geo.py
urbantrips/kpi/__init__.py
urbantrips/kpi/kpi.py
urbantrips/kpi/line_od_matrix.py
urbantrips/kpi/overlapping.py
urbantrips/lineas_deseo/__init__.py
urbantrips/lineas_deseo/lineas_deseo.py
urbantrips/tests/__init__.py
urbantrips/tests/test_routes.py
urbantrips/tests/test_services.py
urbantrips/tests/test_stops.py
urbantrips/tests/test_unit_tests.py
urbantrips/utils/__init__.py
urbantrips/utils/check_configs.py
urbantrips/utils/utils.py
urbantrips/viz/__init__.py
urbantrips/viz/line_od_matrix.py
urbantrips/viz/overlapping.py
urbantrips/viz/viz.py
urbantrips/viz_ppt_utils/__init__.py
urbantrips/viz_ppt_utils/viz_ppt_utils.py
urbantrips-0.3.0.dist-info/LICENSE.md
urbantrips-0.3.0.dist-info/METADATA
urbantrips-0.3.0.dist-info/WHEEL
urbantrips-0.3.0.dist-info/top_level.txt
urbantrips-0.3.0.dist-info/RECORD
