Metadata-Version: 2.1
Name: urbantrips
Version: 0.3.0
Summary: A library to process public transit smart card data.
Home-page: https://github.com/EL-BID/UrbanTrips
Author: Felipe Gonzalez & Sebastian Anapolsky
Author-email: 
Classifier: Programming Language :: Python :: 3
Classifier: Operating System :: OS Independent
Requires-Python: >=3.10
License-File: LICENSE.md
Requires-Dist: anyio
Requires-Dist: contextily
Requires-Dist: folium
Requires-Dist: fiona
Requires-Dist: geopandas
Requires-Dist: fiona
Requires-Dist: h3<4
Requires-Dist: ipython
Requires-Dist: jupyterlab<4.4
Requires-Dist: jupyter
Requires-Dist: libpysal
Requires-Dist: mapclassify
Requires-Dist: matplotlib
Requires-Dist: matplotlib-scalebar
Requires-Dist: notebook
Requires-Dist: numba
Requires-Dist: numpy<2
Requires-Dist: openpyxl
Requires-Dist: osmnx
Requires-Dist: pandas
Requires-Dist: pandana
Requires-Dist: patsy
Requires-Dist: Pillow<11
Requires-Dist: platformdirs
Requires-Dist: plotly
Requires-Dist: python-pptx
Requires-Dist: PyYAML
Requires-Dist: seaborn
Requires-Dist: shapely
Requires-Dist: statsmodels
Requires-Dist: streamlit
Requires-Dist: streamlit-folium
Requires-Dist: typing_extensions
Requires-Dist: weightedstats
Requires-Dist: OSMnet
